edgefirst_client-2.8.0.data/scripts/edgefirst-client
edgefirst_client-2.8.0.dist-info/METADATA
edgefirst_client-2.8.0.dist-info/WHEEL
edgefirst_client/__init__.py
edgefirst_client/__init__.pyi
edgefirst_client/edgefirst_client.abi3.so
edgefirst_client/py.typed
edgefirst_client-2.8.0.dist-info/RECORD
