Metadata-Version: 2.4
Name: edgefirst_client
Version: 2.8.0
Requires-Dist: polars
Home-Page: https://edgefirst.ai
Requires-Python: >=3.8
Project-URL: Homepage, https://edgefirst.studio
Project-URL: Documentation, https://doc.edgefirst.ai
